MANIFEST.in
README.md
setup.py
test.py
wordpress.py
python_wordpress.egg-info/PKG-INFO
python_wordpress.egg-info/SOURCES.txt
python_wordpress.egg-info/dependency_links.txt
python_wordpress.egg-info/requires.txt
python_wordpress.egg-info/top_level.txt