Metadata-Version: 1.0
Name: python-wordpress
Version: 0.1.3
Summary: A Python client for the WordPress JSON API plugin
Home-page: https://github.com/eyeseast/python-wordpress
Author: Chris Amico
Author-email: eyeseast@gmail.com
License: MIT
Platform: UNKNOWN
Classifier: Environment :: Web Environment
Classifier: Intended Audience :: Developers
Classifier: Natural Language :: English
Classifier: Operating System :: OS Independent
Classifier: Programming Language :: Python
Classifier: Topic :: Software Development :: Libraries :: Python Modules
